scrim/__init__.py
scrim/__main__.py
scrim/api.py
scrim/commands.py
scrim/globals.py
scrim/utils.py
scrim/bin/scrim.bat
scrim/bin/scrim.ps1
scrim/bin/scrim.sh
scrim-0.1.0.dist-info/DESCRIPTION.rst
scrim-0.1.0.dist-info/METADATA
scrim-0.1.0.dist-info/RECORD
scrim-0.1.0.dist-info/WHEEL
scrim-0.1.0.dist-info/entry_points.txt
scrim-0.1.0.dist-info/metadata.json
scrim-0.1.0.dist-info/top_level.txt
