Metadata-Version: 2.0
Name: scrim
Version: 0.1.0
Summary: Opaque Python CLI Wrapper
Home-page: https://github.com/danbradham/scrim.git
Author: Dan Bradham
Author-email: danielbradham@gmail.com
License: MIT
Platform: UNKNOWN
Classifier: Development Status :: 4 - Beta
Classifier: Intended Audience :: Developers
Classifier: License :: OSI Approved :: MIT License
Classifier: Operating System :: OS Independent
Classifier: Programming Language :: Python
Classifier: Programming Language :: Python :: 2.7
Classifier: Programming Language :: Python :: 3.2
Classifier: Programming Language :: Python :: 3.3
Classifier: Programming Language :: Python :: 3.4
Classifier: Programming Language :: Python :: 3.5
Classifier: Programming Language :: Python :: 3.6
Classifier: Topic :: Software Development :: Libraries :: Python Modules
Requires-Dist: click (>=6.7)
Requires-Dist: psutil (>=5.2)
Requires-Dist: fstrings (>=0.1.0)
Requires-Dist: six (>=1.10.0)
